PyNotion.py
main.py
models/__init__.py
models/alert_perferences.py
models/base_station.py
models/devices.py
models/event.py
models/firmware.py
models/location.py
models/sensor.py
models/status.py
models/system.py
models/task.py
models/task_data.py
models/threshold.py
models/user.py
models/user_preferences.py
PyNotion-0.0.2.dist-info/METADATA
PyNotion-0.0.2.dist-info/WHEEL
PyNotion-0.0.2.dist-info/top_level.txt
PyNotion-0.0.2.dist-info/RECORD
