Metadata-Version: 2.1
Name: PyNotion
Version: 0.0.2
Summary: Wrapper around Notion API.
Home-page: https://github.com/bradleyhurley/PyNotion
Author: Brad Hurley
Author-email: bradley.hurley@gmail.com
License: license.txt
Platform: UNKNOWN
